{
  "persons": [
    {
      "id": "5760",
      "name": "Difre",
      "number": "0987654"
    },
    {
      "id": "f8b0",
      "name": "Oniy",
      "number": "456789"
    },
    {
      "id": "0787",
      "name": "jeijf",
      "number": "-098765"
    },
    {
      "id": "7ae0",
      "name": "Fredrick",
      "number": "456789"
    },
    {
      "id": "cf45",
      "name": "tgyuhijok",
      "number": "098765"
    },
    {
      "id": "4a3c",
      "name": "serdtfgyuh",
      "number": "sxdctfvygbh"
    },
    {
      "id": "1c41",
      "name": "wesrdtfyg",
      "number": "234567"
    },
    {
      "id": "49bf",
      "name": "wesdrtfgyuh",
      "number": "234567"
    },
    {
      "id": "4819",
      "name": "serdtfgy",
      "number": "234567"
    },
    {
      "id": "2e16",
      "name": "drftgyhuj",
      "number": "234567"
    },
    {
      "id": "514c",
      "name": "",
      "number": ""
    },
    {
      "id": "8f8d",
      "name": "derftgyhuji",
      "number": "2345678"
    },
    {
      "id": "0ee7",
      "name": "wesrdtfgyuh",
      "number": "23456789"
    },
    {
      "id": "b456",
      "name": "Fredrick Onyngo",
      "number": "874627"
    },
    {
      "id": "bc89",
      "name": "Onyango Fredrick",
      "number": ""
    }
  ]
}